bact_bessyii_mls_ophyd/__init__.py
bact_bessyii_mls_ophyd/db/mongo_repository.py
bact_bessyii_mls_ophyd/devices/__init__.py
bact_bessyii_mls_ophyd/devices/process/__init__.py
bact_bessyii_mls_ophyd/devices/process/bpm_packed_data.py
bact_bessyii_mls_ophyd/devices/process/counter_sink.py
bact_bessyii_mls_ophyd/devices/utils/__init__.py
bact_bessyii_mls_ophyd/devices/utils/multiplexer_state_machine.py
bact_bessyii_mls_ophyd/devices/utils/power_converter.py
bact_bessyii_mls_ophyd/devices/utils/power_converters_as_multiplexer.py
bact_bessyii_mls_ophyd/devices/utils/process_vector.py
bact_bessyii_mls_ophyd/devices/utils/reached_setpoint.py
bact_bessyii_mls_ophyd/math/__init__.py
bact_bessyii_mls_ophyd/math/utils.py
bact_bessyii_mls_ophyd-0.2.0.dist-info/LICENSE
bact_bessyii_mls_ophyd-0.2.0.dist-info/METADATA
bact_bessyii_mls_ophyd-0.2.0.dist-info/WHEEL
bact_bessyii_mls_ophyd-0.2.0.dist-info/RECORD
