Metadata-Version: 2.3
Name: bact-bessyii-mls-ophyd
Version: 0.2.0
Summary: Ophyd Devices Common for Bessy II and Metrology Light Source.
License: GPL-3.0
Author: Pierre Schnizer
Requires-Python: >=3.7
Classifier: License :: OSI Approved :: GNU General Public License v3 (GPLv3)
Classifier: Programming Language :: Python :: 3
Classifier: Programming Language :: Python :: 3.7
Classifier: Programming Language :: Python :: 3.8
Classifier: Programming Language :: Python :: 3.9
Classifier: Programming Language :: Python :: 3.10
Classifier: Programming Language :: Python :: 3.11
Classifier: Programming Language :: Python :: 3.12
Classifier: Programming Language :: Python :: 3.13
Requires-Dist: ophyd (>=1.5)
Requires-Dist: pyepics
Project-URL: Documentation, https://github.com/hz-b/bact-bessyii-mls-ophyd.git
Project-URL: Homepage, https://github.com/hz-b/bact-bessyii-mls-ophyd
Project-URL: Repository, https://github.com/hz-b/bact-bessyii-mls-ophyd.git
